Fifty_Flask-1.4.0.dist-info/METADATA
Fifty_Flask-1.4.0.dist-info/RECORD
Fifty_Flask-1.4.0.dist-info/WHEEL
Fifty_Flask-1.4.0.dist-info/top_level.txt
fifty_flask/__init__.py
fifty_flask/app.py
fifty_flask/blueprints.py
fifty_flask/compat.py
fifty_flask/danger.py
fifty_flask/db.py
fifty_flask/queue.py
fifty_flask/script.py
fifty_flask/forms/__init__.py
fifty_flask/forms/mixins.py
fifty_flask/views/__init__.py
fifty_flask/views/generic.py
tests/__init__.py
tests/forms.py
tests/mixins.py
tests/test_danger.py
tests/config/__init__.py
tests/config/mixins.py
tests/config/test_configs.py
tests/views/__init__.py
tests/views/test_cookies.py
tests/views/test_cors.py
tests/views/test_flash.py
tests/views/test_forms.py
tests/views/test_generic.py
tests/views/test_mimetypes.py
tests/views/test_pjax.py
tests/views/test_redirects.py
tests/views/test_response.py
tests/views/test_send_file.py
tests/views/test_templates.py
