Metadata-Version: 2.1
Name: Fifty-Flask
Version: 1.4.0
Summary: Flask enhancements.
Home-page: https://bitbucket.org/50onred/fifty/overview
Author: Craig Slusher
Author-email: craig@50onred.com
License: BSD
Platform: any
Classifier: Environment :: Web Environment
Classifier: Intended Audience :: Developers
Classifier: License :: OSI Approved :: BSD License
Classifier: Operating System :: OS Independent
Classifier: Programming Language :: Python
Classifier: Topic :: Internet :: WWW/HTTP :: Dynamic Content
Classifier: Topic :: Software Development :: Libraries :: Python Modules
Requires-Dist: flask (>=0.11)
